sskw/__init__.py
sskw/tasks/__init__.py
sskw/tasks/all.py
sskw/tasks/audio_format_conversion.py
sskw/tasks/audio_transcription_paraformer.py
sskw/tasks/audio_transcription_paraformer_cpu.py
sskw/tasks/audio_transcription_paraformer_gpu.py
sskw/tasks/audio_transcription_sensevoice.py
sskw/tasks/audio_transcription_sensevoice_cpu.py
sskw/tasks/audio_transcription_sensevoice_gpu.py
sskw/tasks/celery_app.py
sskw/tasks/meeting_summery.py
sskw/tasks/meeting_text_refine.py
sskw/tasks/models.py
sskw_tasks-0.4.2.dist-info/METADATA
sskw_tasks-0.4.2.dist-info/WHEEL
sskw_tasks-0.4.2.dist-info/top_level.txt
sskw_tasks-0.4.2.dist-info/RECORD
