Metadata-Version: 2.4
Name: sskw-tasks
Version: 0.4.2
Summary: sskw shared celery task declaration
Author-email: liwei <491520313@qq.com>
License-Expression: MIT
Project-URL: Homepage, https://tasks.sensearray.com/docs
Requires-Python: >=3.8
Requires-Dist: celery>=5.5.3
Requires-Dist: pydantic>=2.10.6
